innov8-0.1.0b0.dist-info/METADATA
innov8-0.1.0b0.dist-info/WHEEL
innov8-0.1.0b0.dist-info/entry_points.txt
innov8-0.1.0b0.dist-info/licenses/LICENSE
innov8/__init__.py
innov8/__main__.py
innov8/app.py
innov8/components/charts_52w.py
innov8/components/decorators.py
innov8/components/dropdowns.py
innov8/components/intra_sector.py
innov8/components/main_carousel.py
innov8/components/price_card.py
innov8/components/price_chart.py
innov8/components/themes.py
innov8/components/update.py
innov8/db_ops.py
innov8/layout.py
innov8/run.py
innov8/sp500_tickers.txt
innov8/stonks.db
innov8/update_all.py
innov8-0.1.0b0.dist-info/RECORD
