Metadata-Version: 2.1
Name: innov8
Version: 0.1.0b0
Summary: an interactive market dashboard
Author-Email: mayushii21 <122178787+mayushii21@users.noreply.github.com>
License: BSD-3-Clause
Project-URL: Homepage, http://innov8finance.pythonanywhere.com/
Project-URL: Repository, https://github.com/mayushii21/market-dashboard
Project-URL: Bug tracker, https://github.com/mayushii21/market-dashboard/issues
Requires-Python: >=3.10
Requires-Dist: dash[diskcache]==2.16.1
Requires-Dist: dash-bootstrap-components
Requires-Dist: dash-bootstrap-templates
Requires-Dist: dash-tvlwc>=0.1.1
Requires-Dist: dash-trich-components
Requires-Dist: requests
Requires-Dist: beautifulsoup4
Requires-Dist: lxml
Requires-Dist: pandas
Requires-Dist: yfinance
Requires-Dist: tqdm
Requires-Dist: python-dotenv>=1.0.1
Requires-Dist: loguru>=0.7.2
